{
  "generator-jhipster": {
    "blueprints": [],
    "otherModules": [],
    "applicationType": "monolith",
    "reactive": false,
    "baseName": "sample",
    "jhipsterVersion": "6.10.3",
    "skipClient": false,
    "skipServer": false,
    "skipUserManagement": true,
    "skipCheckLengthOfIdentifier": false,
    "skipFakeData": false,
    "jhiPrefix": "jhi",
    "entitySuffix": "",
    "dtoSuffix": "DTO",
    "clientPackageManager": "npm",
    "testFrameworks": [],
    "pages": [],
    "creationTimestamp": 1601048731527,
    "promptValues": {
      "packageName": "io.snyk.bmvermeer.jhipsnyk",
      "nativeLanguage": "en"
    },
    "serviceDiscoveryType": false,
    "authenticationType": "jwt",
    "packageName": "io.snyk.bmvermeer.jhipsnyk",
    "serverPort": "8080",
    "cacheProvider": "ehcache",
    "databaseType": "no",
    "buildTool": "maven",
    "serverSideOptions": [],
    "websocket": false,
    "searchEngine": false,
    "messageBroker": false,
    "enableSwaggerCodegen": false,
    "clientFramework": "angularX",
    "clientTheme": "none",
    "enableTranslation": false,
    "nativeLanguage": "en",
    "packageFolder": "io/snyk/bmvermeer/jhipsnyk",
    "jwtSecretKey": "ZDUyOTA0NDg0NjAxODcyYWYxMWE5MDdjN2JhOTA0MTlkNzI4NGYyMTM3OTFhYjMyNzJjY2U3MTlkZjM2NzljMTRhY2MwYTA1OGU0MzAyZTcyZjVjMTUyM2FiMmQ3MjE5ZDJjODNjMGFjYTA0MzEzYjczMWI1MDgwZGQ4YjE5YjQ=",
    "devDatabaseType": "no",
    "prodDatabaseType": "no",
    "enableHibernateCache": false,
    "clientThemeVariant": "primary",
    "useSass": true,
    "languages": []
  }
}
